allelica_lib/__init__.py
allelica_lib/parse.py
Allelica_pkg_Nico.4D-1.0.3.dist-info/LICENSE
Allelica_pkg_Nico.4D-1.0.3.dist-info/METADATA
Allelica_pkg_Nico.4D-1.0.3.dist-info/WHEEL
Allelica_pkg_Nico.4D-1.0.3.dist-info/top_level.txt
Allelica_pkg_Nico.4D-1.0.3.dist-info/RECORD
