Metadata-Version: 2.1
Name: Allelica-pkg-Nico.4D
Version: 1.0.3
Summary: Allelica Library
Home-page: https://github.com/4DIngenieria/Allelica
Author: Nicolas Alejandro Rodriguez
Author-email: info@4dingenieria.com.ar
License: UNKNOWN
Project-URL: Bug Tracker, https://github.com/4DIngenieria/Allelica
Platform: UNKNOWN
Classifier: Programming Language :: Python :: 3
Classifier: License :: OSI Approved :: MIT License
Classifier: Operating System :: OS Independent
Requires-Python: >=3.8
License-File: LICENSE
Requires-Dist: pandas (==1.2.5)
Requires-Dist: dask (==2021.6.2)
Requires-Dist: openpyxl (==3.0.7)
